wrknoob/__init__.py
wrknoob/wrknoob.py
wrknoob-1.0.11.dist-info/licenses/LICENSE
wrknoob-1.0.11.dist-info/METADATA
wrknoob-1.0.11.dist-info/WHEEL
wrknoob-1.0.11.dist-info/entry_points.txt
wrknoob-1.0.11.dist-info/top_level.txt
wrknoob-1.0.11.dist-info/RECORD
