Metadata-Version: 2.4
Name: wrknoob
Version: 1.0.11
Summary: A simple CLI tool
Author-email: Satish Patra <satish.patra@protonmail.com>
Project-URL: Homepage, https://github.com/sitasp/wrknoob
Project-URL: Bug Tracker, https://github.com/sitasp/wrknoob/issues
Classifier: Programming Language :: Python :: 3
Classifier: License :: OSI Approved :: MIT License
Classifier: Operating System :: OS Independent
Requires-Python: >=3.8
License-File: LICENSE
Requires-Dist: matplotlib
Requires-Dist: rich
Dynamic: license-file
